ccs2/__init__.py
ccs2/__main__.py
ccs2/compile.py
ccs2/generate_code/generate_code.py
ccs2/generate_code/generate_code_utils.py
ccs2/generate_code/tac_generator.py
ccs2/lexical/lexical_analysis.py
ccs2/lexical/lexical_exception.py
ccs2/lexical/lexical_utils.py
ccs2/lexical/token_model.py
ccs2/semantic/semantic_analysis.py
ccs2/semantic/semantic_exception.py
ccs2/semantic/symbol.py
ccs2/syntax/syntax_analysis.py
ccs2/syntax/syntax_exception.py
ccs2/syntax/syntax_expects.py
ccs2/syntax/syntax_utils.py
ccs2/utils/logger.py
ccs2/utils/singleton.py
generate_code/generate_code.py
generate_code/generate_code_utils.py
generate_code/tac_generator.py
lexical/lexical_analysis.py
lexical/lexical_exception.py
lexical/lexical_utils.py
lexical/token_model.py
semantic/semantic_analysis.py
semantic/semantic_exception.py
semantic/symbol.py
syntax/syntax_analysis.py
syntax/syntax_exception.py
syntax/syntax_expects.py
syntax/syntax_utils.py
utils/logger.py
utils/singleton.py
ccs2-1.0.0.dist-info/METADATA
ccs2-1.0.0.dist-info/WHEEL
ccs2-1.0.0.dist-info/entry_points.txt
ccs2-1.0.0.dist-info/top_level.txt
ccs2-1.0.0.dist-info/RECORD
