Metadata-Version: 2.1
Name: ccs2
Version: 1.0.0
Summary: C Compiler Simulator
Home-page: UNKNOWN
Author: Umberto Barros
License: MIT
Platform: UNKNOWN
